{
  "version": 1,
  "valid": true,
  "name": "Lay on side",
  "description": "Come here often?",
  "author": "Gray",
  "emote": {
    "beginTick": 0,
    "endTick": 60,
    "stopTick": 61,
    "isLoop": true,
    "returnTick": 2,
    "nsfw": false,
    "degrees": false,
    "moves": [
      {
        "tick": 9,
        "easing": "INOUTQUAD",
        "head": {
          "x": 0.032940164
        }
      },
      {
        "tick": 9,
        "easing": "INOUTQUAD",
        "head": {
          "y": 0.65296936
        }
      },
      {
        "tick": 9,
        "easing": "INOUTQUAD",
        "head": {
          "z": -4.5121737E-8
        }
      },
      {
        "tick": 9,
        "easing": "INOUTQUAD",
        "head": {
          "pitch": -0.058931645
        }
      },
      {
        "tick": 9,
        "easing": "INOUTQUAD",
        "head": {
          "yaw": 0.07322874
        }
      },
      {
        "tick": 9,
        "easing": "INOUTQUAD",
        "head": {
          "roll": -0.4840651
        }
      },
      {
        "tick": 9,
        "easing": "INOUTQUAD",
        "rightLeg": {
          "x": -2.797068
        }
      },
      {
        "tick": 60,
        "easing": "INOUTQUAD",
        "rightLeg": {
          "x": -2.797068
        }
      },
      {
        "tick": 9,
        "easing": "INOUTQUAD",
        "rightLeg": {
          "y": 11.436219
        }
      },
      {
        "tick": 60,
        "easing": "INOUTQUAD",
        "rightLeg": {
          "y": 11.436219
        }
      },
      {
        "tick": 9,
        "easing": "INOUTQUAD",
        "rightLeg": {
          "z": 0.09999982
        }
      },
      {
        "tick": 60,
        "easing": "INOUTQUAD",
        "rightLeg": {
          "z": 0.09999982
        }
      },
      {
        "tick": 9,
        "easing": "INOUTQUAD",
        "rightLeg": {
          "pitch": 0.29903716
        }
      },
      {
        "tick": 60,
        "easing": "INOUTQUAD",
        "rightLeg": {
          "pitch": 0.29903716
        }
      },
      {
        "tick": 9,
        "easing": "INOUTQUAD",
        "rightLeg": {
          "yaw": 0.14198887
        }
      },
      {
        "tick": 60,
        "easing": "INOUTQUAD",
        "rightLeg": {
          "yaw": 0.14198887
        }
      },
      {
        "tick": 9,
        "easing": "INOUTQUAD",
        "rightLeg": {
          "roll": -0.23576786
        }
      },
      {
        "tick": 60,
        "easing": "INOUTQUAD",
        "rightLeg": {
          "roll": -0.23576786
        }
      },
      {
        "tick": 9,
        "easing": "INOUTQUAD",
        "rightArm": {
          "x": -4.747883
        }
      },
      {
        "tick": 60,
        "easing": "INOUTQUAD",
        "rightArm": {
          "x": -4.747883
        }
      },
      {
        "tick": 9,
        "easing": "INOUTQUAD",
        "rightArm": {
          "y": 3.1810217
        }
      },
      {
        "tick": 60,
        "easing": "INOUTQUAD",
        "rightArm": {
          "y": 3.1810217
        }
      },
      {
        "tick": 9,
        "easing": "INOUTQUAD",
        "rightArm": {
          "z": -3.6616484E-8
        }
      },
      {
        "tick": 60,
        "easing": "INOUTQUAD",
        "rightArm": {
          "z": -3.6616484E-8
        }
      },
      {
        "tick": 9,
        "easing": "INOUTQUAD",
        "rightArm": {
          "pitch": 0.088438146
        }
      },
      {
        "tick": 60,
        "easing": "INOUTQUAD",
        "rightArm": {
          "pitch": 0.088438146
        }
      },
      {
        "tick": 9,
        "easing": "INOUTQUAD",
        "rightArm": {
          "yaw": 0.059682917
        }
      },
      {
        "tick": 34,
        "easing": "INOUTQUAD",
        "rightArm": {
          "yaw": 0.05968292
        }
      },
      {
        "tick": 60,
        "easing": "INOUTQUAD",
        "rightArm": {
          "yaw": 0.059682917
        }
      },
      {
        "tick": 9,
        "easing": "INOUTQUAD",
        "rightArm": {
          "roll": -0.11930333
        }
      },
      {
        "tick": 34,
        "easing": "INOUTQUAD",
        "rightArm": {
          "roll": -0.07667829
        }
      },
      {
        "tick": 60,
        "easing": "INOUTQUAD",
        "rightArm": {
          "roll": -0.11930333
        }
      },
      {
        "tick": 9,
        "easing": "INOUTQUAD",
        "leftArm": {
          "x": 5.4667325
        }
      },
      {
        "tick": 60,
        "easing": "INOUTQUAD",
        "leftArm": {
          "x": 5.4667325
        }
      },
      {
        "tick": 9,
        "easing": "INOUTQUAD",
        "leftArm": {
          "y": 2.091978
        }
      },
      {
        "tick": 60,
        "easing": "INOUTQUAD",
        "leftArm": {
          "y": 2.091978
        }
      },
      {
        "tick": 9,
        "easing": "INOUTQUAD",
        "leftArm": {
          "z": 1.15473455E-7
        }
      },
      {
        "tick": 60,
        "easing": "INOUTQUAD",
        "leftArm": {
          "z": 1.15473455E-7
        }
      },
      {
        "tick": 9,
        "easing": "INOUTQUAD",
        "leftArm": {
          "pitch": 2.5832847E-7
        }
      },
      {
        "tick": 60,
        "easing": "INOUTQUAD",
        "leftArm": {
          "pitch": 2.5832847E-7
        }
      },
      {
        "tick": 9,
        "easing": "INOUTQUAD",
        "leftArm": {
          "yaw": 5.18057E-8
        }
      },
      {
        "tick": 60,
        "easing": "INOUTQUAD",
        "leftArm": {
          "yaw": 5.18057E-8
        }
      },
      {
        "tick": 9,
        "easing": "INOUTQUAD",
        "leftArm": {
          "roll": -3.537426
        }
      },
      {
        "tick": 60,
        "easing": "INOUTQUAD",
        "leftArm": {
          "roll": -3.537426
        }
      },
      {
        "tick": 9,
        "easing": "INOUTQUAD",
        "leftLeg": {
          "x": 1.8636016
        }
      },
      {
        "tick": 60,
        "easing": "INOUTQUAD",
        "leftLeg": {
          "x": 1.8636016
        }
      },
      {
        "tick": 9,
        "easing": "INOUTQUAD",
        "leftLeg": {
          "y": 12.379825
        }
      },
      {
        "tick": 60,
        "easing": "INOUTQUAD",
        "leftLeg": {
          "y": 12.379825
        }
      },
      {
        "tick": 9,
        "easing": "INOUTQUAD",
        "leftLeg": {
          "z": -0.10000005
        }
      },
      {
        "tick": 60,
        "easing": "INOUTQUAD",
        "leftLeg": {
          "z": -0.10000005
        }
      },
      {
        "tick": 9,
        "easing": "INOUTQUAD",
        "leftLeg": {
          "pitch": 2.4451863E-9
        }
      },
      {
        "tick": 60,
        "easing": "INOUTQUAD",
        "leftLeg": {
          "pitch": 2.4451863E-9
        }
      },
      {
        "tick": 9,
        "easing": "INOUTQUAD",
        "leftLeg": {
          "yaw": 2.5516407E-8
        }
      },
      {
        "tick": 60,
        "easing": "INOUTQUAD",
        "leftLeg": {
          "yaw": 2.5516407E-8
        }
      },
      {
        "tick": 9,
        "easing": "INOUTQUAD",
        "leftLeg": {
          "roll": 0.19107288
        }
      },
      {
        "tick": 60,
        "easing": "INOUTQUAD",
        "leftLeg": {
          "roll": 0.19107288
        }
      },
      {
        "tick": 9,
        "easing": "INOUTQUAD",
        "body": {
          "x": 0.24776529
        }
      },
      {
        "tick": 60,
        "easing": "INOUTQUAD",
        "body": {
          "x": 0.24776529
        }
      },
      {
        "tick": 9,
        "easing": "INOUTQUAD",
        "body": {
          "y": -0.48562008
        }
      },
      {
        "tick": 60,
        "easing": "INOUTQUAD",
        "body": {
          "y": -0.48562008
        }
      },
      {
        "tick": 9,
        "easing": "INOUTQUAD",
        "body": {
          "z": 6.524735E-8
        }
      },
      {
        "tick": 60,
        "easing": "INOUTQUAD",
        "body": {
          "z": 6.524735E-8
        }
      },
      {
        "tick": 9,
        "easing": "INOUTQUAD",
        "body": {
          "pitch": -1.0838065E-7
        }
      },
      {
        "tick": 60,
        "easing": "INOUTQUAD",
        "body": {
          "pitch": -1.0838065E-7
        }
      },
      {
        "tick": 9,
        "easing": "INOUTQUAD",
        "body": {
          "yaw": -1.3182347E-7
        }
      },
      {
        "tick": 60,
        "easing": "INOUTQUAD",
        "body": {
          "yaw": -1.3182347E-7
        }
      },
      {
        "tick": 9,
        "easing": "INOUTQUAD",
        "body": {
          "roll": 1.3762215
        }
      },
      {
        "tick": 60,
        "easing": "INOUTQUAD",
        "body": {
          "roll": 1.3762215
        }
      }
    ]
  }
}