{
  "biomesoplenty:recipes/transportation/willow_boat": {
    "criteria": {
      "in_water": "2025-02-14 08:18:38 +0000"
    },
    "done": true
  },
  "create:root": {
    "criteria": {
      "0": "2025-02-14 08:16:31 +0000"
    },
    "done": true
  },
  "minecraft:recipes/transportation/cherry_boat": {
    "criteria": {
      "in_water": "2025-02-14 08:18:38 +0000"
    },
    "done": true
  },
  "biomesoplenty:recipes/transportation/umbran_boat": {
    "criteria": {
      "in_water": "2025-02-14 08:18:38 +0000"
    },
    "done": true
  },
  "minecraft:recipes/transportation/bamboo_raft": {
    "criteria": {
      "in_water": "2025-02-14 08:18:38 +0000"
    },
    "done": true
  },
  "biomesoplenty:recipes/transportation/dead_boat": {
    "criteria": {
      "in_water": "2025-02-14 08:18:38 +0000"
    },
    "done": true
  },
  "biomesoplenty:recipes/transportation/magic_boat": {
    "criteria": {
      "in_water": "2025-02-14 08:18:38 +0000"
    },
    "done": true
  },
  "iceandfire:iceandfire/root": {
    "criteria": {
      "tick": "2025-02-14 08:16:31 +0000"
    },
    "done": true
  },
  "dungeons_arise:wda_root": {
    "criteria": {
      "WDA": "2025-02-14 08:16:31 +0000"
    },
    "done": true
  },
  "biomesoplenty:biomesoplenty/root": {
    "criteria": {
      "forested_field": "2025-02-14 08:16:32 +0000"
    },
    "done": true
  },
  "minecraft:recipes/transportation/acacia_boat": {
    "criteria": {
      "in_water": "2025-02-14 08:18:38 +0000"
    },
    "done": true
  },
  "mca:root": {
    "criteria": {
      "village_plains": "2025-02-14 08:17:37 +0000"
    },
    "done": true
  },
  "minecraft:recipes/transportation/jungle_boat": {
    "criteria": {
      "in_water": "2025-02-14 08:18:38 +0000"
    },
    "done": true
  },
  "twilightforest:recipes/transportation/twilight_oak_boat": {
    "criteria": {
      "in_water": "2025-02-14 08:18:38 +0000"
    },
    "done": true
  },
  "twilightforest:recipes/transportation/time_boat": {
    "criteria": {
      "in_water": "2025-02-14 08:18:38 +0000"
    },
    "done": true
  },
  "twilightforest:recipes/transportation/mining_boat": {
    "criteria": {
      "in_water": "2025-02-14 08:18:38 +0000"
    },
    "done": true
  },
  "orcz:orczchallenge": {
    "criteria": {
      "orczchallenge": "2025-02-14 08:16:31 +0000"
    },
    "done": true
  },
  "dungeons_arise:find_keep_kayra": {
    "criteria": {
      "location0": "2025-02-14 08:25:49 +0000"
    },
    "done": true
  },
  "twilightforest:recipes/transportation/mangrove_boat": {
    "criteria": {
      "in_water": "2025-02-14 08:18:38 +0000"
    },
    "done": true
  },
  "biomesoplenty:recipes/transportation/fir_boat": {
    "criteria": {
      "in_water": "2025-02-14 08:18:38 +0000"
    },
    "done": true
  },
  "twilightforest:recipes/transportation/transformation_boat": {
    "criteria": {
      "in_water": "2025-02-14 08:18:38 +0000"
    },
    "done": true
  },
  "biomesoplenty:biomesoplenty/all_biomes": {
    "criteria": {
      "shrubland": "2025-02-14 08:18:54 +0000",
      "forested_field": "2025-02-14 08:16:32 +0000"
    },
    "done": false
  },
  "minecraft:recipes/transportation/spruce_boat": {
    "criteria": {
      "in_water": "2025-02-14 08:18:38 +0000"
    },
    "done": true
  },
  "minecraft:recipes/transportation/birch_boat": {
    "criteria": {
      "in_water": "2025-02-14 08:18:38 +0000"
    },
    "done": true
  },
  "minecraft:recipes/transportation/oak_boat": {
    "criteria": {
      "in_water": "2025-02-14 08:18:38 +0000"
    },
    "done": true
  },
  "biomesoplenty:recipes/transportation/redwood_boat": {
    "criteria": {
      "in_water": "2025-02-14 08:18:38 +0000"
    },
    "done": true
  },
  "cataclysm:root": {
    "criteria": {
      "custom_test_name": "2025-02-14 08:16:31 +0000"
    },
    "done": true
  },
  "minecraft:recipes/transportation/mangrove_boat": {
    "criteria": {
      "in_water": "2025-02-14 08:18:38 +0000"
    },
    "done": true
  },
  "biomesoplenty:recipes/transportation/hellbark_boat": {
    "criteria": {
      "in_water": "2025-02-14 08:18:38 +0000"
    },
    "done": true
  },
  "biomesoplenty:recipes/transportation/jacaranda_boat": {
    "criteria": {
      "in_water": "2025-02-14 08:18:38 +0000"
    },
    "done": true
  },
  "twilightforest:recipes/transportation/canopy_boat": {
    "criteria": {
      "in_water": "2025-02-14 08:18:38 +0000"
    },
    "done": true
  },
  "biomesoplenty:recipes/transportation/mahogany_boat": {
    "criteria": {
      "in_water": "2025-02-14 08:18:38 +0000"
    },
    "done": true
  },
  "twilightforest:recipes/transportation/dark_boat": {
    "criteria": {
      "in_water": "2025-02-14 08:18:38 +0000"
    },
    "done": true
  },
  "biomesoplenty:recipes/transportation/palm_boat": {
    "criteria": {
      "in_water": "2025-02-14 08:18:38 +0000"
    },
    "done": true
  },
  "minecraft:adventure/adventuring_time": {
    "criteria": {
      "minecraft:river": "2025-02-14 08:17:37 +0000"
    },
    "done": false
  },
  "twilightforest:recipes/transportation/sorting_boat": {
    "criteria": {
      "in_water": "2025-02-14 08:18:38 +0000"
    },
    "done": true
  },
  "minecraft:recipes/transportation/dark_oak_boat": {
    "criteria": {
      "in_water": "2025-02-14 08:18:38 +0000"
    },
    "done": true
  },
  "DataVersion": 3465
}